llmgateway/__init__.py
llmgateway/client.py
llmgateway/models.py
llmgateway_sdk-0.1.1.dist-info/METADATA
llmgateway_sdk-0.1.1.dist-info/WHEEL
llmgateway_sdk-0.1.1.dist-info/licenses/LICENSE
llmgateway_sdk-0.1.1.dist-info/RECORD
