Metadata-Version: 2.4
Name: llmgateway-sdk
Version: 0.1.1
Summary: LLMGateway Python SDK Client
Project-URL: Homepage, https://github.com/yezz123/llmgateway-py-sdk
Project-URL: Documentation, https://docs.llmgateway.io/
Project-URL: Funding, https://github.com/sponsors/yezz123
Project-URL: Source, https://github.com/yezz123/llmgateway-py-sdk
Author-email: Yasser Tahiri <hello@yezz.me>
License-Expression: MIT
License-File: LICENSE
Keywords: LLM,LLMGateway,LLMGateway API,LLMGateway Python Client,LLMGateway Python SDK,LLMGateway Python SDK Client,LLMGateway SDK
Classifier: Development Status :: 4 - Beta
Classifier: Framework :: AsyncIO
Classifier: Framework :: Pydantic
Classifier: Framework :: Pydantic :: 2
Classifier: Intended Audience :: Developers
Classifier: Intended Audience :: Information Technology
Classifier: License :: OSI Approved :: MIT License
Classifier: Operating System :: OS Independent
Classifier: Programming Language :: Python
Classifier: Programming Language :: Python :: 3
Classifier: Programming Language :: Python :: 3 :: Only
Classifier: Programming Language :: Python :: 3.9
Classifier: Programming Language :: Python :: 3.10
Classifier: Programming Language :: Python :: 3.11
Classifier: Programming Language :: Python :: 3.12
Classifier: Programming Language :: Python :: 3.13
Classifier: Topic :: Internet
Classifier: Topic :: Internet :: WWW/HTTP :: Session
Classifier: Topic :: Software Development :: Libraries :: Python Modules
Classifier: Typing :: Typed
Requires-Python: >=3.9
Requires-Dist: httpx>=0.28.0
Requires-Dist: pydantic>=2.0.0
